solarannotator/__init__.py
solarannotator/config.py
solarannotator/gui.py
solarannotator/io.py
solarannotator/main.py
solarannotator/template.py
solarannotator-1.0.1.data/data/solarannotator/default.json
solarannotator-1.0.1.dist-info/METADATA
solarannotator-1.0.1.dist-info/WHEEL
solarannotator-1.0.1.dist-info/entry_points.txt
solarannotator-1.0.1.dist-info/top_level.txt
solarannotator-1.0.1.dist-info/RECORD
