Metadata-Version: 2.1
Name: solarannotator
Version: 1.0.1
Summary: A tool to annotate images of the Sun
Home-page: 
Author: J. Marcus Hughes
Author-email: j-marcus.hughes@noaa.gov
Requires-Dist: PyQt5
Requires-Dist: matplotlib
Requires-Dist: astropy
Requires-Dist: numpy
Requires-Dist: goes-solar-retriever
Requires-Dist: scipy
Requires-Dist: scikit-image
Requires-Dist: pillow
Requires-Dist: sunpy
Requires-Dist: lxml
Requires-Dist: reproject
Requires-Dist: zeep
Requires-Dist: drms
